idem_aws/conf.py
idem_aws/version.py
idem_aws/acct/aws/gsuite.py
idem_aws/acct/aws/iam.py
idem_aws/acct/aws/init.py
idem_aws/acct/aws/contracts/init.py
idem_aws/acct/metadata/aws.py
idem_aws/autogen/aws/function.py
idem_aws/autogen/aws/init.py
idem_aws/autogen/aws/known_params.py
idem_aws/autogen/aws/param.py
idem_aws/autogen/aws/plugin.py
idem_aws/autogen/aws/possible_functions.py
idem_aws/autogen/aws/resource.py
idem_aws/autogen/aws/service.py
idem_aws/esm/aws.py
idem_aws/esm/contracts/aws.py
idem_aws/exec/aws/arn.py
idem_aws/exec/aws/data.py
idem_aws/exec/aws/acm/certificate_manager.py
idem_aws/exec/aws/apigateway/base_path_mapping.py
idem_aws/exec/aws/apigateway/deployment.py
idem_aws/exec/aws/apigateway/domain_name.py
idem_aws/exec/aws/apigateway/integration.py
idem_aws/exec/aws/apigateway/integration_response.py
idem_aws/exec/aws/apigateway/method.py
idem_aws/exec/aws/apigateway/method_response.py
idem_aws/exec/aws/apigateway/resource.py
idem_aws/exec/aws/apigateway/rest_api.py
idem_aws/exec/aws/apigateway/stage.py
idem_aws/exec/aws/apigatewayv2/api.py
idem_aws/exec/aws/apigatewayv2/authorizer.py
idem_aws/exec/aws/apigatewayv2/domain_name.py
idem_aws/exec/aws/apigatewayv2/integration.py
idem_aws/exec/aws/apigatewayv2/route.py
idem_aws/exec/aws/application_autoscaling/scalable_target.py
idem_aws/exec/aws/application_autoscaling/scaling_policy.py
idem_aws/exec/aws/autoscaling/scaling_policy.py
idem_aws/exec/aws/backup/backup_vault.py
idem_aws/exec/aws/budgets/budget.py
idem_aws/exec/aws/cloudformation/stack.py
idem_aws/exec/aws/cloudfront/cache_policy.py
idem_aws/exec/aws/cloudfront/distribution.py
idem_aws/exec/aws/cloudfront/origin_request_policy.py
idem_aws/exec/aws/cloudwatch/log_group.py
idem_aws/exec/aws/cloudwatchlogs/resource_policy.py
idem_aws/exec/aws/config/configuration_aggregator.py
idem_aws/exec/aws/costexplorer/cost_allocation_tag.py
idem_aws/exec/aws/docdb/db_cluster.py
idem_aws/exec/aws/docdb/db_cluster_parameter_group.py
idem_aws-6.2.1.dist-info/LICENSE
idem_aws-6.2.1.dist-info/METADATA
idem_aws-6.2.1.dist-info/WHEEL
idem_aws-6.2.1.dist-info/top_level.txt
idem_aws-6.2.1.dist-info/RECORD
