Metadata-Version: 2.1
Name: idem-aws
Version: 6.2.1
Summary: AWS Cloud Provider for Idem
Home-page: https://docs.idemproject.io/idem-aws/en/latest/index.html
Author: VMware, Inc.
Author-email: idemproject@vmware.com
License: Apache Software License 2.0
Project-URL: Code, https://gitlab.com/vmware/idem/idem-aws
Project-URL: Issue tracker, https://gitlab.com/vmware/idem/idem-aws/-/issues
Classifier: Environment :: Console
Classifier: Intended Audience :: Developers
Classifier: Intended Audience :: Information Technology
Classifier: Intended Audience :: System Administrators
Classifier: Operating System :: OS Independent
Classifier: Programming Language :: Python
Classifier: Programming Language :: Python :: 3.8
Classifier: Programming Language :: Python :: 3.8
Classifier: Programming Language :: Python :: 3.9
Classifier: Programming Language :: Python :: 3.10
Classifier: Programming Language :: Python :: 3.11
Classifier: Development Status :: 5 - Production/Stable
Classifier: License :: OSI Approved :: Apache Software License
Requires-Python: >=3.8
License-File: LICENSE
Requires-Dist: acct <9.0.0,>=8.3.3
Requires-Dist: dict-toolbox >=3.1.1
Requires-Dist: boto3 <1.27.0,>=1.25.0
Requires-Dist: idem <26.0.0,>=21.0.0
Requires-Dist: pgpy <0.7.0,>=0.6.0
Requires-Dist: deepdiff <7.0.0,>=6.3.0
Requires-Dist: pop-serial <2.0.0,>=1.1.0
Requires-Dist: cryptography <42.0.0,>=39.0.1
Provides-Extra: autogen
Requires-Dist: pop-create-idem ==4.4.3 ; extra == 'autogen'
Requires-Dist: inflect ; extra == 'autogen'
Requires-Dist: textwrap3 ; extra == 'autogen'
Requires-Dist: tqdm ; extra == 'autogen'
Provides-Extra: bootstrap
Requires-Dist: heist-salt <6.0.0,>=5.3.1 ; extra == 'bootstrap'
Provides-Extra: full
Requires-Dist: aws-google-auth >=0.0.35 ; extra == 'full'
Requires-Dist: heist-salt <6.0.0,>=5.3.1 ; extra == 'full'
Requires-Dist: textwrap3 ; extra == 'full'
Requires-Dist: pop-create-idem ==4.4.3 ; extra == 'full'
Requires-Dist: localstack-ext ; extra == 'full'
Requires-Dist: localstack-client ; extra == 'full'
Requires-Dist: tqdm ; extra == 'full'
Requires-Dist: localstack ; extra == 'full'
Requires-Dist: msgpack ; extra == 'full'
Requires-Dist: heist <7.0.0,>=6.1.0 ; extra == 'full'
Requires-Dist: inflect ; extra == 'full'
Provides-Extra: google_auth
Requires-Dist: aws-google-auth >=0.0.35 ; extra == 'google_auth'
Requires-Dist: msgpack ; extra == 'google_auth'
Provides-Extra: heist
Requires-Dist: heist <7.0.0,>=6.1.0 ; extra == 'heist'
Provides-Extra: localstack
Requires-Dist: localstack ; extra == 'localstack'
Requires-Dist: localstack-ext ; extra == 'localstack'
Requires-Dist: localstack-client ; extra == 'localstack'
